aqseq/__init__.py
aqseq/__version__.py
aqseq/_version/__init__.py
aqseq/_version/version.json
aqseq/archived/config.json
aqseq/archived/conversion.py
aqseq/archived/sequence_manager.py
aqseq/connectors/__init__.py
aqseq/connectors/abc.py
aqseq/connectors/benchling.py
aqseq/dna.py
aqseq/exceptions.py
aqseq/logger.py
aqseq/scripts.py
aqseq-0.1.6.dist-info/entry_points.txt
aqseq-0.1.6.dist-info/WHEEL
aqseq-0.1.6.dist-info/METADATA
aqseq-0.1.6.dist-info/RECORD
