Metadata-Version: 2.1
Name: aqseq
Version: 0.1.6
Summary: sequence manager for Aquarium and Benchling
Home-page: https://www.github.com/jvrana/AqSequenceManager
Author: Justin Vrana
Author-email: justin.vrana@gmail.com
Requires-Python: >=3.7,<4.0
Classifier: Programming Language :: Python :: 3
Classifier: Programming Language :: Python :: 3.7
Requires-Dist: benchlingapi (>=2.0.0a0,<3.0.0)
Requires-Dist: bs4 (>=0.0.1,<0.0.2)
Requires-Dist: inflection (>=0.3.1,<0.4.0)
Requires-Dist: jdna (>=0.1.2,<0.2.0)
Requires-Dist: loggable-jdv (>=0.1.2,<0.2.0)
Requires-Dist: pydent (==0.1.5a6)
Requires-Dist: requests (>=2.22,<3.0)
Requires-Dist: urlopen (>=1.0,<2.0)
Project-URL: Documentation, https://www.github.com/jvrana/AqSequenceManager
Project-URL: Repository, https://www.github.com/jvrana/AqSequenceManager
